dz15/__init__.py
dz15/main.py
hw15-0.0.1.dist-info/LICENSE
hw15-0.0.1.dist-info/METADATA
hw15-0.0.1.dist-info/WHEEL
hw15-0.0.1.dist-info/top_level.txt
hw15-0.0.1.dist-info/RECORD
