Metadata-Version: 2.1
Name: hw15
Version: 0.0.1
Summary: Doing homework 15
Home-page: https://github.com/vemelyanov07/hw15.git
Author: vemelyanov
Author-email: vemelyanov@mail.ru
License: UNKNOWN
Platform: UNKNOWN
Classifier: Programming Language :: Python :: 3.8
Classifier: License :: OSI Approved :: MIT License
Classifier: Operating System :: OS Independent
Requires-Python: >=3.8
License-File: LICENSE
